README.md
setup.cfg
setup.py
LoveUpdate/__init__.py
LoveUpdate/report.py
LoveUpdate/update.py
LoveUpdate.egg-info/PKG-INFO
LoveUpdate.egg-info/SOURCES.txt
LoveUpdate.egg-info/dependency_links.txt
LoveUpdate.egg-info/requires.txt
LoveUpdate.egg-info/top_level.txt