Metadata-Version: 2.1
Name: LoveUpdate
Version: 0.0.3
Summary: Autoupdate package for LovelacePM
Home-page: https://github.com/pedrosecchi67/LoveUpdate
Author: Pedro de Almeida Secchi
Author-email: pedrosecchimail@gmail.com
License: UNKNOWN
Platform: UNKNOWN
Classifier: Programming Language :: Python :: 3
Classifier: License :: OSI Approved :: GNU General Public License (GPL)
Classifier: Operating System :: OS Independent
Requires-Python: >=3.6
